{
  "$schema": "https://developer.microsoft.com/json-schemas/fabric/item/report/definition/visualContainer/2.5.0/schema.json",
  "name": "3aca1b9b690f0d62f3f3",
  "position": {
    "x": 10.350404312668463,
    "y": 0,
    "z": 0,
    "height": 280.32345013477089,
    "width": 841.832884097035,
    "tabOrder": 0
  },
  "visual": {
    "visualType": "clusteredColumnChart",
    "query": {
      "queryState": {
        "Category": {
          "projections": [
            {
              "field": {
                "HierarchyLevel": {
                  "Expression": {
                    "Hierarchy": {
                      "Expression": {
                        "PropertyVariationSource": {
                          "Expression": {
                            "SourceRef": {
                              "Entity": "Sales"
                            }
                          },
                          "Name": "Variation",
                          "Property": "DeliveryDueDate"
                        }
                      },
                      "Hierarchy": "Date Hierarchy"
                    }
                  },
                  "Level": "Year"
                }
              },
              "queryRef": "Sales.DeliveryDueDate.Variation.Date Hierarchy.Year",
              "nativeQueryRef": "DeliveryDueDate Year",
              "active": true
            }
          ]
        },
        "Y": {
          "projections": [
            {
              "field": {
                "Aggregation": {
                  "Expression": {
                    "Column": {
                      "Expression": {
                        "SourceRef": {
                          "Entity": "Sales"
                        }
                      },
                      "Property": "_Profit"
                    }
                  },
                  "Function": 0
                }
              },
              "queryRef": "Sum(Sales._Profit)",
              "nativeQueryRef": "_Profit"
            }
          ]
        }
      },
      "sortDefinition": {
        "sort": [
          {
            "field": {
              "HierarchyLevel": {
                "Expression": {
                  "Hierarchy": {
                    "Expression": {
                      "PropertyVariationSource": {
                        "Expression": {
                          "SourceRef": {
                            "Entity": "Sales"
                          }
                        },
                        "Name": "Variation",
                        "Property": "DeliveryDueDate"
                      }
                    },
                    "Hierarchy": "Date Hierarchy"
                  }
                },
                "Level": "Year"
              }
            },
            "direction": "Ascending"
          }
        ],
        "isDefaultSort": true
      }
    },
    "drillFilterOtherVisuals": true
  }
}