{
  "$schema": "https://developer.microsoft.com/json-schemas/fabric/item/report/definition/visualContainer/2.5.0/schema.json",
  "name": "ed0f8c590b6ceb9bea3a",
  "position": {
    "x": 64,
    "y": 339,
    "z": 1,
    "height": 280,
    "width": 279,
    "tabOrder": 1
  },
  "visual": {
    "visualType": "cardVisual",
    "query": {
      "queryState": {
        "Data": {
          "projections": [
            {
              "field": {
                "Measure": {
                  "Expression": {
                    "SourceRef": {
                      "Entity": "_Calculations"
                    }
                  },
                  "Property": "ProfitMarginRatio"
                }
              },
              "queryRef": "_Calculations.ProfitMarginRatio",
              "nativeQueryRef": "ProfitMarginRatio"
            }
          ]
        }
      },
      "sortDefinition": {
        "sort": [
          {
            "field": {
              "Measure": {
                "Expression": {
                  "SourceRef": {
                    "Entity": "_Calculations"
                  }
                },
                "Property": "ProfitMarginRatio"
              }
            },
            "direction": "Descending"
          }
        ],
        "isDefaultSort": true
      }
    },
    "drillFilterOtherVisuals": true
  }
}